[
  {
    "id": "1024",
    "name": "1024",
    "type": "Hybrid",
    "typeDetails": "Sativa 70% / Indica 30%",
    "genetics": "Geheim (Medical Seeds)",
    "thc": 22.5,
    "cbd": 2.5,
    "thcRange": "20-25%",
    "cbdRange": "1-4%",
    "floweringTime": 12,
    "floweringTimeRange": "11-13",
    "description": "Eine mysteriöse, Sativa-dominante Sorte, bekannt für eine energetisierende, zerebrale und kreative Wirkung, die in eine entspannende Körperentspannung übergeht. Ideal für aktive Tage. Das Aroma ist moschusartig, süß und würzig, ähnlich wie Weihrauch oder grüner Tee.",
    "aromas": ["Würzig", "Kräuter", "Süß", "Moschus", "Weihrauch"],
    "dominantTerpenes": ["Terpinolen", "Caryophyllen", "Pinen"],
    "agronomic": {
      "difficulty": "Medium",
      "yield": "High",
      "height": "Tall",
      "yieldDetails": { "indoor": "~600 g/m^2", "outdoor": "600-800 g/Pflanze" },
      "heightDetails": { "outdoor": "bis 3.5 m" }
    }
  },
  {
    "id": "24k-gold",
    "name": "24k Gold",
    "type": "Hybrid",
    "typeDetails": "Indica 60% / Sativa 40%",
    "genetics": "Kosher Kush x Tangie",
    "thc": 22,
    "cbd": 1,
    "thcRange": "18-26%",
    "cbdRange": "<1%",
    "floweringTime": 9.5,
    "floweringTimeRange": "9-10",
    "description": "Alias: Kosher Tangie. Gezüchtet von DNA Genetics. Beginnt mit einem euphorischen, kreativen Rausch (Sativa-Einfluss), der in eine tiefe, entspannende Körperwirkung übergeht (Indica-Einfluss). Ideal zum Stressabbau. Die Knospen sind oft goldfarben und sehr harzig.",
    "aromas": ["Zitrus", "Orange", "Süß", "Erdig", "Würzig"],
    "dominantTerpenes": ["Myrcen", "Limonen", "Caryophyllen"],
    "agronomic": {
      "difficulty": "Medium",
      "yield": "Medium",
      "height": "Medium",
      "yieldDetails": { "indoor": "450-550 g/m^2", "outdoor": "Mittel-Hoch" },
      "heightDetails": { "outdoor": "Hoch (bis 2 m), benötigt Training" }
    }
  },
  {
    "id": "303-og",
    "name": "303 OG",
    "type": "Hybrid",
    "typeDetails": "Indica 60% / Sativa 40%",
    "genetics": "Pre-98 Bubba Kush x Chemdawg",
    "thc": 22,
    "cbd": 1,
    "thcRange": "18-26%",
    "cbdRange": "<1%",
    "floweringTime": 9.5,
    "floweringTimeRange": "9-10",
    "description": "Alias: 303 Kush. Eine Colorado-Sorte, benannt nach der Vorwahl von Denver. Bietet eine entspannende Körperwirkung, die Verspannungen löst, während der Geist klar und gesellig bleibt. Ideal für soziale Anlässe am Abend. Aroma von Kaffee, Diesel und Gewürzen.",
    "aromas": ["Holzig", "Erdig", "Scharf", "Kaffee", "Diesel"],
    "dominantTerpenes": ["Limonen", "Myrcen", "Linalool"],
    "agronomic": {
      "difficulty": "Medium",
      "yield": "Low",
      "height": "Short",
      "yieldDetails": { "indoor": "~300 g/m^2", "outdoor": "~350 g/Pflanze" },
      "heightDetails": { "indoor": "Kurz bis Mittel" }
    }
  },
  {
    "id": "501st-og",
    "name": "501st OG",
    "type": "Hybrid",
    "typeDetails": "Indica 70% / Sativa 30%",
    "genetics": "Skywalker OG x Rare Dankness #1",
    "thc": 21.5,
    "cbd": 1,
    "thcRange": "17-26%",
    "cbdRange": "<1%",
    "floweringTime": 8,
    "floweringTimeRange": "7-9",
    "description": "Gezüchtet von Rare Dankness. Bekannt für farbenfrohe Knospen mit Grün-, Blau- und Violetttönen. Die Indica-dominante Wirkung ist stark beruhigend und sedierend, ideal für die Nacht zur Schmerzlinderung und bei Schlaflosigkeit. Beginnt euphorisch, bevor die schwere Körperwirkung einsetzt.",
    "aromas": ["Kiefer", "Erdig", "Scharf", "Traube", "Süß"],
    "dominantTerpenes": ["Myrcen", "Caryophyllen", "Limonen"],
    "agronomic": {
      "difficulty": "Medium",
      "yield": "Medium",
      "height": "Medium",
      "yieldDetails": { "indoor": "350-900 g/m^2", "outdoor": "~400 g/Pflanze" },
      "heightDetails": { "indoor": "Kurz (~75 cm)", "outdoor": "Hoch (~200 cm)" }
    }
  },
  {
    "id": "707-headband",
    "name": "707 Headband",
    "type": "Hybrid",
    "typeDetails": "Sativa 70% / Indica 30%",
    "genetics": "Sour Diesel x OG Kush x Master Kush",
    "thc": 22.5,
    "cbd": 1,
    "thcRange": "19-26%",
    "cbdRange": "<1%",
    "floweringTime": 9.5,
    "floweringTimeRange": "9-10",
    "description": "Benannt nach der Vorwahl von Humboldt County, CA. Erzeugt ein charakteristisches Druckgefühl um den Kopf (\"Headband\"). Die Wirkung ist ausgewogen, zerebral anregend und kreativ, aber auch körperlich entspannend. Ideal zur Linderung.",
    "aromas": ["Kiefer", "Diesel", "Erdig", "Zitrus", "Würzig"],
    "dominantTerpenes": ["Myrcen", "Limonen", "Caryophyllen"],
    "agronomic": {
      "difficulty": "Medium",
      "yield": "High",
      "height": "Tall",
      "yieldDetails": { "indoor": "500-600 g/m^2", "outdoor": "900-4000 g/Pflanze" },
      "heightDetails": { "outdoor": "Hoch" }
    }
  },
  {
    "id": "8-ball-kush",
    "name": "8 Ball Kush",
    "type": "Indica",
    "typeDetails": "Indica 100%",
    "genetics": "Afghanische Landrasse (Afghanistan x Pakistan)",
    "thc": 18.5,
    "cbd": 3,
    "thcRange": "15-22%",
    "cbdRange": "1-5%",
    "floweringTime": 8,
    "floweringTimeRange": "7-9",
    "description": "Eine reine Indica von Barney's Farm aus der Hindu-Kush-Region. Erzeugt eine tiefe, körperliche Entspannung und einen klaren, zerebralen Rausch, der für eine Indica ungewöhnlich anregend sein kann. Ideal zur Schmerzlinderung. Produziert extrem viel Harz.",
    "aromas": ["Erdig", "Würzig", "Kiefer", "Holzig", "Süß"],
    "dominantTerpenes": ["Myrcen", "Pinen", "Caryophyllen"],
    "agronomic": {
      "difficulty": "Easy",
      "yield": "Medium",
      "height": "Short",
      "yieldDetails": { "indoor": "450-550 g/m^2", "outdoor": "bis 600 g/Pflanze" },
      "heightDetails": { "indoor": "Kurz (80-110 cm)" }
    }
  },
  {
    "id": "9-pound-hammer",
    "name": "9 Pound Hammer",
    "type": "Hybrid",
    "typeDetails": "Indica 80% / Sativa 20%",
    "genetics": "Gooberry x Hells OG x Jack the Ripper",
    "thc": 20,
    "cbd": 1,
    "thcRange": "17-23%",
    "cbdRange": "~1%",
    "floweringTime": 8,
    "floweringTimeRange": "7-9",
    "description": "Gezüchtet von Jinxproof Genetics. Der Name deutet auf die schwere, lang anhaltende Wirkung hin (\"Couch-Lock\"). Führt zu tiefer körperlicher Entspannung und Sedierung, ideal bei Schmerzen und Stress.",
    "aromas": ["Süß", "Traube", "Limette", "Kiefer", "Erdig"],
    "dominantTerpenes": ["Myrcen", "Pinen", "Caryophyllen"],
    "agronomic": {
      "difficulty": "Easy",
      "yield": "High",
      "height": "Medium",
      "yieldDetails": { "indoor": "Hoch" },
      "heightDetails": { "indoor": "Mittel" }
    }
  }
]
